sort/__init__.py
sort/main.py
gojyuuonjyunn-1.0.dist-info/LICENSE
gojyuuonjyunn-1.0.dist-info/METADATA
gojyuuonjyunn-1.0.dist-info/WHEEL
gojyuuonjyunn-1.0.dist-info/top_level.txt
gojyuuonjyunn-1.0.dist-info/RECORD
