Metadata-Version: 2.1
Name: gojyuuonjyunn
Version: 1.0
Summary: Simple Wrapper to Sort Japanese Strings in Gojyuuonjyunn Order
Home-page: https://github.com/Sakkyoku-Sha/gojyuuonjyunn
Author: Ryan Anderson
Author-email: ryananderson0147@gmail.com
Classifier: Programming Language :: Python :: 3
Classifier: License :: OSI Approved :: MIT License
Classifier: Operating System :: OS Independent
Requires-Python: >=3.6
License-File: LICENSE
Requires-Dist: pykakasi
